ghcs/__init__.py
ghcs/cli.py
ghcs/downloader.py
ghcs/extractor.py
ghcs/search.py
ghcs-1.0.1.dist-info/LICENSE
ghcs-1.0.1.dist-info/METADATA
ghcs-1.0.1.dist-info/WHEEL
ghcs-1.0.1.dist-info/entry_points.txt
ghcs-1.0.1.dist-info/top_level.txt
ghcs-1.0.1.dist-info/RECORD
