Metadata-Version: 2.2
Name: ghcs
Version: 1.0.1
Summary: GitHub Code Search CLI with file downloading capability.
Home-page: https://github.com/hissain/ghcs
Author: Md. Sazzad Hissain Khan
Author-email: "Md. Sazzad Hissain Khan" <hissain.khan@gmail.com>
License: MIT
Project-URL: Homepage, https://github.com/hissain/ghcs
Project-URL: Repository, https://github.com/hissain/ghcs
Project-URL: Issues, https://github.com/hissain/ghcs/issues
Classifier: Programming Language :: Python :: 3
Classifier: License :: OSI Approved :: MIT License
Requires-Python: >=3.7
License-File: LICENSE
Requires-Dist: requests
Requires-Dist: python-dotenv
Requires-Dist: google-generativeai
Requires-Dist: nbconvert
Dynamic: author
Dynamic: classifier
Dynamic: home-page
